bucket_pull/__init__.py
bucket_pull/__main__.py
bucket_pull/cli.py
bucket_pull-0.0.2.dist-info/METADATA
bucket_pull-0.0.2.dist-info/WHEEL
bucket_pull-0.0.2.dist-info/entry_points.txt
bucket_pull-0.0.2.dist-info/top_level.txt
bucket_pull-0.0.2.dist-info/RECORD
