Metadata-Version: 2.1
Name: bucket-pull
Version: 0.0.2
Requires-Dist: google-cloud-storage
Requires-Dist: argparse
Requires-Dist: urllib3
